{"code": "d = {\"one\": 1, \"two\": 2, \"three\": 3}\n\nkey_iterator = iter(d)\nvalue_iterator = iter(d.values())\n\nprint(next(key_iterator))\nprint(next(key_iterator))\nprint(next(value_iterator))\nprint(next(value_iterator))", "trace": [{"line": 1, "event": "step_line", "func_name": "<module>", "globals": {}, "ordered_globals": [], "stack_to_render": [], "heap": {}, "stdout": ""}, {"line": 3, "event": "step_line", "func_name": "<module>", "globals": {"d": ["REF", 1]}, "ordered_globals": ["d"], "stack_to_render": [], "heap": {"1": ["DICT", ["one", 1], ["two", 2], ["three", 3]]}, "stdout": ""}, {"line": 4, "event": "step_line", "func_name": "<module>", "globals": {"d": ["REF", 1], "key_iterator": ["REF", 2]}, "ordered_globals": ["d", "key_iterator"], "stack_to_render": [], "heap": {"1": ["DICT", ["one", 1], ["two", 2], ["three", 3]], "2": ["INSTANCE", "dict_keyiterator"]}, "stdout": ""}, {"line": 6, "event": "step_line", "func_name": "<module>", "globals": {"d": ["REF", 1], "key_iterator": ["REF", 2], "value_iterator": ["REF", 3]}, "ordered_globals": ["d", "key_iterator", "value_iterator"], "stack_to_render": [], "heap": {"1": ["DICT", ["one", 1], ["two", 2], ["three", 3]], "2": ["INSTANCE", "dict_keyiterator"], "3": ["INSTANCE", "dict_valueiterator"]}, "stdout": ""}, {"line": 7, "event": "step_line", "func_name": "<module>", "globals": {"d": ["REF", 1], "key_iterator": ["REF", 2], "value_iterator": ["REF", 3]}, "ordered_globals": ["d", "key_iterator", "value_iterator"], "stack_to_render": [], "heap": {"1": ["DICT", ["one", 1], ["two", 2], ["three", 3]], "2": ["INSTANCE", "dict_keyiterator"], "3": ["INSTANCE", "dict_valueiterator"]}, "stdout": "one\n"}, {"line": 8, "event": "step_line", "func_name": "<module>", "globals": {"d": ["REF", 1], "key_iterator": ["REF", 2], "value_iterator": ["REF", 3]}, "ordered_globals": ["d", "key_iterator", "value_iterator"], "stack_to_render": [], "heap": {"1": ["DICT", ["one", 1], ["two", 2], ["three", 3]], "2": ["INSTANCE", "dict_keyiterator"], "3": ["INSTANCE", "dict_valueiterator"]}, "stdout": "one\ntwo\n"}, {"line": 9, "event": "step_line", "func_name": "<module>", "globals": {"d": ["REF", 1], "key_iterator": ["REF", 2], "value_iterator": ["REF", 3]}, "ordered_globals": ["d", "key_iterator", "value_iterator"], "stack_to_render": [], "heap": {"1": ["DICT", ["one", 1], ["two", 2], ["three", 3]], "2": ["INSTANCE", "dict_keyiterator"], "3": ["INSTANCE", "dict_valueiterator"]}, "stdout": "one\ntwo\n1\n"}, {"line": 9, "event": "return", "func_name": "<module>", "globals": {"d": ["REF", 1], "key_iterator": ["REF", 2], "value_iterator": ["REF", 3]}, "ordered_globals": ["d", "key_iterator", "value_iterator"], "stack_to_render": [], "heap": {"1": ["DICT", ["one", 1], ["two", 2], ["three", 3]], "2": ["INSTANCE", "dict_keyiterator"], "3": ["INSTANCE", "dict_valueiterator"]}, "stdout": "one\ntwo\n1\n2\n"}]}